gptko/__init__.py
gptko/kogpt2/__init__.py
gptko/kogpt2/mxnet_kogpt2.py
gptko/kogpt2/pytorch_kogpt2.py
gptko/kogpt2/utils.py
gptko/kogpt2/model/__init__.py
gptko/kogpt2/model/gpt.py
gptko/kogpt2/model/torch_gpt2.py
gptko-0.0.1.dist-info/DESCRIPTION.rst
gptko-0.0.1.dist-info/METADATA
gptko-0.0.1.dist-info/RECORD
gptko-0.0.1.dist-info/WHEEL
gptko-0.0.1.dist-info/metadata.json
gptko-0.0.1.dist-info/top_level.txt
