Metadata-Version: 2.0
Name: gptko
Version: 0.0.1
Summary: from skt AI
Home-page: https://github.com/ssorry123/KOGPT222.git
Author: swp
Author-email: syd03160@gmail.com
License: UNKNOWN
Keywords: pypi deploy
Platform: UNKNOWN
Classifier: Programming Language :: Python :: 3
Classifier: Programming Language :: Python :: 3.2
Classifier: Programming Language :: Python :: 3.3
Classifier: Programming Language :: Python :: 3.4
Classifier: Programming Language :: Python :: 3.5
Classifier: Programming Language :: Python :: 3.6
Classifier: Programming Language :: Python :: 3.7
Requires-Python: >=3
